gradio_dataframe_download/__init__.py
gradio_dataframe_download/component.py
gradio_dataframe_download/component.pyi
gradio_dataframe_download/templates/component/index.js
gradio_dataframe_download/templates/component/style.css
gradio_dataframe_download-0.0.1.dist-info/METADATA
gradio_dataframe_download-0.0.1.dist-info/WHEEL
gradio_dataframe_download-0.0.1.dist-info/licenses/LICENSE.md
gradio_dataframe_download-0.0.1.dist-info/RECORD
