Metadata-Version: 2.4
Name: gradio_dataframe_download
Version: 0.0.1
Summary: A `gradio` component for stateless DataFrame download as CSV.
Project-URL: Repository, https://github.com/andyrids/gradio-dataframe-download
Project-URL: Issues, https://github.com/andyrids/gradio-dataframe-download/-/issues
Author-email: Andrew Ridyard <andyrids.uncapped698@passmail.net>
Maintainer-email: Andrew Ridyard <andyrids.uncapped698@passmail.net>
License-Expression: Apache-2.0
License-File: LICENSE.md
Keywords: button,dataframe,download,gradio-custom-component,stateless
Classifier: Development Status :: 4 - Beta
Classifier: Operating System :: OS Independent
Classifier: Programming Language :: Python :: 3
Classifier: Programming Language :: Python :: 3 :: Only
Classifier: Programming Language :: Python :: 3.9
Classifier: Programming Language :: Python :: 3.10
Classifier: Programming Language :: Python :: 3.11
Classifier: Topic :: Scientific/Engineering
Classifier: Topic :: Scientific/Engineering :: Artificial Intelligence
Classifier: Topic :: Scientific/Engineering :: Visualization
Requires-Python: >=3.10
Requires-Dist: gradio
Requires-Dist: narwhals>=1.42.1
Provides-Extra: dev
Requires-Dist: build; extra == 'dev'
Requires-Dist: twine; extra == 'dev'
